api_library/GetExchangeMessages.py
api_library/GetExchangeSnapshot.py
api_library/GetExchanges.py
api_library/GetExpiryDates.py
api_library/GetHistory.py
api_library/GetInstrumentTypes.py
api_library/GetInstruments.py
api_library/GetInstrumentsOnSearch.py
api_library/GetLastQuote.py
api_library/GetLastQuoteArray.py
api_library/GetLastQuoteArrayOptionGreeks.py
api_library/GetLastQuoteArrayShort.py
api_library/GetLastQuoteArrayShortWithClose.py
api_library/GetLastQuoteOptionChain.py
api_library/GetLastQuoteOptionGreeks.py
api_library/GetLastQuoteOptionGreeksChain.py
api_library/GetLastQuoteShort.py
api_library/GetLastQuoteShortWithClose.py
api_library/GetLimitation.py
api_library/GetMarketMessages.py
api_library/GetOptionTypes.py
api_library/GetProducts.py
api_library/GetServerInfo.py
api_library/GetSnapshot.py
api_library/GetStrikePrices.py
api_library/__init__.py
api_library/base_api.py
api_library/exchanges.py
restgfdl-py/GetExchangeMessages.py
restgfdl-py/GetExchangeSnapshot.py
restgfdl-py/GetExchanges.py
restgfdl-py/GetExpiryDates.py
restgfdl-py/GetHistory.py
restgfdl-py/GetInstrumentTypes.py
restgfdl-py/GetInstruments.py
restgfdl-py/GetInstrumentsOnSearch.py
restgfdl-py/GetLastQuote.py
restgfdl-py/GetLastQuoteArray.py
restgfdl-py/GetLastQuoteArrayOptionGreeks.py
restgfdl-py/GetLastQuoteArrayShort.py
restgfdl-py/GetLastQuoteArrayShortWithClose.py
restgfdl-py/GetLastQuoteOptionChain.py
restgfdl-py/GetLastQuoteOptionGreeks.py
restgfdl-py/GetLastQuoteOptionGreeksChain.py
restgfdl-py/GetLastQuoteShort.py
restgfdl-py/GetLastQuoteShortWithClose.py
restgfdl-py/GetLimitation.py
restgfdl-py/GetMarketMessages.py
restgfdl-py/GetOptionTypes.py
restgfdl-py/GetProducts.py
restgfdl-py/GetServerInfo.py
restgfdl-py/GetSnapshot.py
restgfdl-py/GetStrikePrices.py
restgfdl-py/__init__.py
restgfdl-py/base_api.py
restgfdl_py-1.0.0.dist-info/METADATA
restgfdl_py-1.0.0.dist-info/WHEEL
restgfdl_py-1.0.0.dist-info/top_level.txt
restgfdl_py-1.0.0.dist-info/RECORD
