Metadata-Version: 2.1
Name: restgfdl-py
Version: 1.0.0
Summary: Package to implement REST API of Global Datafeeds
Author: Surendran M
Author-email: surendran.m@globaldatafeeds.in
Classifier: Programming Language :: Python :: 3
Classifier: License :: OSI Approved :: MIT License
Classifier: Operating System :: OS Independent
Requires-Python: >=3.6
Requires-Dist: requests
